pystt/__init__.py
pystt/stt.py
pystt/utils.py
pystt/tests/__init__.py
pystt/tests/test_stt.py
pystt/tests/test_utils.py
pystt-0.2.0.dist-info/DESCRIPTION.rst
pystt-0.2.0.dist-info/METADATA
pystt-0.2.0.dist-info/RECORD
pystt-0.2.0.dist-info/WHEEL
pystt-0.2.0.dist-info/metadata.json
pystt-0.2.0.dist-info/top_level.txt
