Metadata-Version: 2.0
Name: pystt
Version: 0.2.0
Summary: pystt is the serialization and de-serialization library of STT.
Home-page: https://github.com/dust8/pystt
Author: UNKNOWN
Author-email: UNKNOWN
License: MIT
Keywords: pystt stt serialization de-serialization
Platform: UNKNOWN
